a_selenium_add_special_keys/LICENSE
a_selenium_add_special_keys/README.MD
a_selenium_add_special_keys/__init__.py
a_selenium_add_special_keys/requirements.txt
a_selenium_add_special_keys/thirdparty.json
a_selenium_add_special_keys-0.10.dist-info/LICENSE.rst
a_selenium_add_special_keys-0.10.dist-info/METADATA
a_selenium_add_special_keys-0.10.dist-info/WHEEL
a_selenium_add_special_keys-0.10.dist-info/top_level.txt
a_selenium_add_special_keys-0.10.dist-info/RECORD
